{
  "id": "9",
  "titel": "Granola met yoghurt",
  "ingrediënten": [
    {"naam": "volle yoghurt", "hoeveelheid": "250g"},
    {"naam": "zelfgemaakte granola", "hoeveelheid": "60g"},
    {"naam": "honing", "hoeveelheid": "1 el"},
    {"naam": "aardbeien", "hoeveelheid": "40g, in plakjes"},
    {"naam": "blauwe bessen", "hoeveelheid": "30g"},
    {"naam": "banaan", "hoeveelheid": "1/2, in plakjes"},
    {"naam": "chiazaad", "hoeveelheid": "1 tl"},
    {"naam": "walnoten", "hoeveelheid": "1 el, grof gehakt"},
    {"naam": "kokosrasp", "hoeveelheid": "1 tl"},
    {"naam": "pure chocolade", "hoeveelheid": "10g, geraspt (optioneel)"}
  ],
  "stappen": [
    {"stapNummer": 1, "beschrijving": "Maak de granola: meng havervlokken, noten, zaden, kokos en honing. Bak 20 minuten op 170°C tot goudbruin. Laat afkoelen.", "duur": 25},
    {"stapNummer": 2, "beschrijving": "Snijd het fruit en hak de walnoten grof.", "duur": 2},
    {"stapNummer": 3, "beschrijving": "Doe de yoghurt in een kom. Roer het chiazaad erdoor.", "duur": 1},
    {"stapNummer": 4, "beschrijving": "Verdeel de helft van de granola over de yoghurt.", "duur": 1},
    {"stapNummer": 5, "beschrijving": "Voeg aardbeien, blauwe bessen en banaan toe.", "duur": 1},
    {"stapNummer": 6, "beschrijving": "Strooi de rest van de granola, walnoten en kokosrasp erover.", "duur": 1},
    {"stapNummer": 7, "beschrijving": "Garneer met honing en eventueel geraspte pure chocolade.", "duur": 1},
    {"stapNummer": 8, "beschrijving": "Serveer direct als ontbijt of gezond tussendoortje.", "duur": 1}
  ],
  "tags": ["ontbijt", "gezond"],
  "bereidingstijd": 30,
  "moeilijkheid": "middel"
}
